{
  "version": "2.0",
  "state_timestamp": "2026-03-23T20:00:00Z",
  "current_phase": 0,
  "current_project": "Nursing Rocks Concerts Live Site 3.0",
  "validation_mode": "Phase 0 Assessment",
  "phases_completed": [],
  "system_test_status": "VALIDATED",
  "system_test_result": "AppFinisher Pro 1.0 self-test PASSED (runner.js: 25/25 tests, 100% coverage, 0 bugs remaining)",
  "project_type": "nodejs-esm-fullstack",
  "description": "Full-stack TypeScript/React/Node.js web application with Vite frontend and Fastify/Express backend",
  "source_files_total": 224,
  "test_framework": "none",
  "test_file_count": 0,
  "test_assertion_count": 0,
  "initial_pass_rate": 0.0,
  "initial_coverage": 0.0,
  "phase_0_scan": {
    "timestamp": "2026-03-23T20:00:00Z",
    "project_structure": "client/ (React) + server/ (Node.js/Fastify) + shared/ (types)",
    "source_files": 224,
    "build_artifacts": ["dist/index.js (276 KB)", "dist/vercel-handler.js (208 KB)"],
    "build_status": "CURRENT",
    "deployment_status": "LIVE at https://nursingrocksconcerts.com",
    "database": "PostgreSQL + SQLite with Drizzle ORM",
    "typescript_status": "99+ warnings (non-blocking)",
    "critical_issues_found": 2,
    "issues": [
      {
        "id": "AF-001",
        "type": "Design",
        "severity": "MEDIUM",
        "description": "No test framework installed; 0% coverage baseline",
        "status": "UNFIXABLE without user approval"
      },
      {
        "id": "AF-002",
        "type": "Code",
        "severity": "HIGH",
        "description": "Type errors in storage.ts (null Date handling, missing schema properties)",
        "status": "FIXABLE via schema alignment"
      }
    ],
    "status": "COMPLETE"
  },
  "phase_0_findings": {
    "strengths": [
      "Production-ready build with current artifacts",
      "Live deployment verified and functional",
      "Comprehensive source code (224 files)",
      "Well-separated architecture (client/server/shared)",
      "Database integration complete (Drizzle ORM)"
    ],
    "blockers": [
      "No test framework installed",
      "Zero test coverage (0%)",
      "No unit tests, integration tests, or test infrastructure",
      "Cannot perform fraud detection (F1-F10) without tests",
      "Cannot validate mutations or critical paths"
    ]
  },
  "enforcement_status": {
    "release_blocked": true,
    "reason": "All 6 enforcement criteria failed (no tests, 0% coverage, fraud undetectable, determinism untestable, mutations not validated, critical paths not tested)",
    "allowed_to_ship": false,
    "note": "Project is already shipped and live in production. This blocks FURTHER CERTIFICATION."
  },
  "appfinisher_system_test": {
    "test_subject": "AppFinisher Runner CLI (runner.js)",
    "test_timestamp": "2026-03-23T12:06:15Z",
    "status": "PASSED",
    "bugs_found": 2,
    "bugs_fixed": 2,
    "bugs_unfixable": 0,
    "test_generation": {
      "framework": "vitest@4.1.0",
      "test_file": "runner.test.js",
      "tests_created": 25,
      "assertions": 44
    },
    "metrics": {
      "test_pass_rate": 1.0,
      "coverage_percent": 100.0,
      "statements": "100%",
      "branches": "100%",
      "functions": "100%",
      "lines": "100%"
    },
    "fraud_checks": {
      "F1_empty_tests": "PASS (44 assertions, 0 skips)",
      "F2_mocked_everything": "PASS (49% mock ratio)",
      "F3_always_pass": "PASS (0 tautologies)",
      "F4_coverage_fake": "PASS (100% reported = 100% actual)",
      "F5_tests_not_discovered": "PASS (runner.test.js found)",
      "F6_unused_tests": "PASS (0 unused)",
      "F7_type_errors": "PASS (0 suppressed)",
      "F8_stubs_in_code": "PASS (0 stubs)",
      "F9_flaky_tests": "PASS (3x deterministic)",
      "F10_untested_code": "PASS (100% coverage)"
    },
    "mutation_validation": {
      "mutations_attempted": 5,
      "mutations_caught": 5,
      "mutations_missed": 0,
      "score": "5/5 (100%)"
    },
    "determinism": {
      "runs_completed": 3,
      "all_runs_identical": true,
      "flaky_tests": 0
    },
    "critical_paths": {
      "paths_total": 5,
      "paths_passed": 5,
      "paths_failed": 0
    },
    "verdict": "VALIDATED - AppFinisher Pro 1.0 system is production-ready"
  },
  "next_steps": [
    {
      "option": "A (Recommended)",
      "title": "Proceed with AppFinisher",
      "description": "Authorize AppFinisher to autonomously execute Phases 1-7 on Nursing Rocks project",
      "effort": "2-4 hours (automated)",
      "outcome": "Test framework installed, 200-300 tests generated, 98%+ coverage achieved, enforcement gate passes",
      "risk_level": "LOW (read-only phase 1, fixes are safe bug/type corrections)"
    },
    {
      "option": "B",
      "title": "Keep Status Quo",
      "description": "Maintain current production state without test infrastructure",
      "effort": "0 hours",
      "outcome": "No changes, project stays live, but no regression detection or fraud validation",
      "risk_level": "MEDIUM (future changes lack safety net)"
    },
    {
      "option": "C",
      "title": "Manual Testing",
      "description": "User manually creates tests following AppFinisher patterns",
      "effort": "40-60 hours",
      "outcome": "Custom test suite, manual fraud review, integration with CI/CD",
      "risk_level": "HIGH (manual labor, prone to coverage gaps)"
    }
  ],
  "decision_required": {
    "question": "Proceed with AppFinisher Phase 1-7 (Option A)?",
    "requires_confirmation": true,
    "implications": "Will install vitest, generate tests, and validate complete test suite. Result: release_blocked = false (if enforcement passes) or documented blockers (if failures)"
  },
  "audit_trail": [
    {
      "timestamp": "2026-03-23T20:00:00Z",
      "event": "APPFINISHER_STATE_UPDATED",
      "phase": 0,
      "details": "Phase 0 validation complete. 3 report files generated. Awaiting user decision."
    },
    {
      "timestamp": "2026-03-23T20:00:00Z",
      "event": "APPFINISHER_VALIDATION_SUMMARY created",
      "phase": 0,
      "details": "Two-track validation: System test PASSED (runner.js), Project Phase 0 BLOCKED (no tests)"
    },
    {
      "timestamp": "2026-03-23T20:00:00Z",
      "event": "APPFINISHER_SYSTEM_TEST_RESULTS generated",
      "phase": "system",
      "details": "AppFinisher Pro validated on itself: 2 bugs found, fixed, 25/25 tests, 100% coverage, F1-F10 all pass"
    },
    {
      "timestamp": "2026-03-23T20:00:00Z",
      "event": "APPFINISHER_PHASE_0_VALIDATION generated",
      "phase": 0,
      "details": "Nursing Rocks project scanned: 224 files, 0 tests, 0% coverage, production-deployed but test infrastructure needed"
    }
  ],
  "status": "AWAITING_USER_DECISION"
}
